video_pygame/__init__.py
video_pygame/data_control.py
video_pygame/main.py
video_pygame/video.py
video_injection_pygame-0.0.3.dist-info/LICENSE
video_injection_pygame-0.0.3.dist-info/METADATA
video_injection_pygame-0.0.3.dist-info/WHEEL
video_injection_pygame-0.0.3.dist-info/top_level.txt
video_injection_pygame-0.0.3.dist-info/RECORD
