Metadata-Version: 2.1
Name: video-injection-pygame
Version: 0.0.3
Summary: Inject mp4 videos into your pygame surface
Home-page: https://github.com/RDMchik/VideoInjectionPyGame
Author: rdmchik
Author-email: denkickgames@gmail.com
Project-URL: Bug Tracker, https://github.com/RDMchik/VideoInjectionPyGame/issues
Classifier: Programming Language :: Python :: 3
Classifier: License :: OSI Approved :: MIT License
Classifier: Operating System :: OS Independent
Requires-Python: >=3.6
License-File: LICENSE
